simple_python_app_qt/__init__.py
simple_python_app_qt/_version.py
simple_python_app_qt/property.py
simple_python_app_qt/py.typed
simple_python_app_qt/qml_application.py
simple_python_app_qt/resources/default_logging_config.yaml
simple_python_app_qt-0.1.1.dist-info/LICENSE
simple_python_app_qt-0.1.1.dist-info/METADATA
simple_python_app_qt-0.1.1.dist-info/WHEEL
simple_python_app_qt-0.1.1.dist-info/top_level.txt
simple_python_app_qt-0.1.1.dist-info/RECORD
