Metadata-Version: 2.1
Name: simple_python_app_qt
Version: 0.1.1
Summary: Small framework based on simple_python_app that simplifies Python Qt app creation.
Home-page: https://github.com/twyleg/simple_python_app_qt
Author: Torsten Wylegala
Author-email: mail@twyleg.de
License: GPL 3.0
Keywords: framework boilerplate logging argparse config qt qml pyside
License-File: LICENSE
Requires-Dist: simple_python_app~=0.4.1
Requires-Dist: pyside6~=6.7.2
